amd_cupy/__init__.py
amd_cupy-0.0.2.dist-info/METADATA
amd_cupy-0.0.2.dist-info/WHEEL
amd_cupy-0.0.2.dist-info/top_level.txt
amd_cupy-0.0.2.dist-info/RECORD
