Metadata-Version: 2.4
Name: amd-cupy
Version: 0.0.2
Summary: CuPy: NumPy & SciPy for GPU
Author-email: AMD <support@amd.com>
License: MIT License
Project-URL: Homepage, https://cupy.dev/
Project-URL: Documentation, https://docs.cupy.dev/
Requires-Python: >=3.8
